{"type":"FeatureCollection","metadata":{"totalCount":14},"features":[{
  "geometry": {
    "type": "Point", 
    "coordinates": [
      7.3, 
      50.36, 
      -15.0
    ]
  }, 
  "type": "Feature", 
  "id": "20140225_0000095", 
  "properties": {
    "lastupdate": "2014-02-26T10:03:00.0Z", 
    "magtype": "ml", 
    "evtype": "ke", 
    "lon": 7.3, 
    "auth": "BGR", 
    "lat": 50.36, 
    "depth": 15.0, 
    "unid": "20140225_0000095", 
    "mag": 2.0, 
    "time": "2014-02-25T11:02:03.9Z", 
    "source_id": "361963", 
    "source_catalog": "EMSC-RTS", 
    "flynn_region": "GERMANY"
  }
},{
  "geometry": {
    "type": "Point", 
    "coordinates": [
      7.73, 
      46.29, 
      -5.0
    ]
  }, 
  "type": "Feature", 
  "id": "20140225_0000004", 
  "properties": {
    "lastupdate": "2014-02-25T01:03:00.0Z", 
    "magtype": "ml", 
    "evtype": "ke", 
    "lon": 7.73, 
    "auth": "EMSC", 
    "lat": 46.29, 
    "depth": 5.0, 
    "unid": "20140225_0000004", 
    "mag": 3.1, 
    "time": "2014-02-25T00:52:45.9Z", 
    "source_id": "361688", 
    "source_catalog": "EMSC-RTS", 
    "flynn_region": "SWITZERLAND"
  }
},{
  "geometry": {
    "type": "Point", 
    "coordinates": [
      8.35, 
      46.91, 
      1.0
    ]
  }, 
  "type": "Feature", 
  "id": "20140218_0000048", 
  "properties": {
    "lastupdate": "2014-02-18T13:57:00.0Z", 
    "magtype": "ml", 
    "evtype": "ke", 
    "lon": 8.35, 
    "auth": "ZUR", 
    "lat": 46.91, 
    "depth": -1.0, 
    "unid": "20140218_0000048", 
    "mag": 1.7, 
    "time": "2014-02-18T13:53:38.4Z", 
    "source_id": "360528", 
    "source_catalog": "EMSC-RTS", 
    "flynn_region": "SWITZERLAND"
  }
},{
  "geometry": {
    "type": "Point", 
    "coordinates": [
      7.06, 
      47.29, 
      -3.0
    ]
  }, 
  "type": "Feature", 
  "id": "20140218_0000026", 
  "properties": {
    "lastupdate": "2014-02-18T08:57:00.0Z", 
    "magtype": "ml", 
    "evtype": "ke", 
    "lon": 7.06, 
    "auth": "ZUR", 
    "lat": 47.29, 
    "depth": 3.0, 
    "unid": "20140218_0000026", 
    "mag": 1.9, 
    "time": "2014-02-18T08:52:32.6Z", 
    "source_id": "360458", 
    "source_catalog": "EMSC-RTS", 
    "flynn_region": "SWITZERLAND"
  }
},{
  "geometry": {
    "type": "Point", 
    "coordinates": [
      9.8, 
      47.55, 
      -17.0
    ]
  }, 
  "type": "Feature", 
  "id": "20140218_0000005", 
  "properties": {
    "lastupdate": "2014-02-18T01:29:00.0Z", 
    "magtype": "ml", 
    "evtype": "ke", 
    "lon": 9.8, 
    "auth": "ZUR", 
    "lat": 47.55, 
    "depth": 17.0, 
    "unid": "20140218_0000005", 
    "mag": 1.8, 
    "time": "2014-02-18T01:26:35.5Z", 
    "source_id": "360414", 
    "source_catalog": "EMSC-RTS", 
    "flynn_region": "AUSTRIA"
  }
},{
  "geometry": {
    "type": "Point", 
    "coordinates": [
      8.14, 
      46.33, 
      -2.0
    ]
  }, 
  "type": "Feature", 
  "id": "20140217_0000035", 
  "properties": {
    "lastupdate": "2014-02-17T10:05:00.0Z", 
    "magtype": "ml", 
    "evtype": "ke", 
    "lon": 8.14, 
    "auth": "ZUR", 
    "lat": 46.33, 
    "depth": 2.0, 
    "unid": "20140217_0000035", 
    "mag": 1.9, 
    "time": "2014-02-17T09:34:59.7Z", 
    "source_id": "360300", 
    "source_catalog": "EMSC-RTS", 
    "flynn_region": "SWITZERLAND"
  }
},{
  "geometry": {
    "type": "Point", 
    "coordinates": [
      6.74, 
      46.82, 
      0.0
    ]
  }, 
  "type": "Feature", 
  "id": "20140217_0000032", 
  "properties": {
    "lastupdate": "2014-02-17T09:45:00.0Z", 
    "magtype": "ml", 
    "evtype": "ke", 
    "lon": 6.74, 
    "auth": "ZUR", 
    "lat": 46.82, 
    "depth": 0.0, 
    "unid": "20140217_0000032", 
    "mag": 1.7, 
    "time": "2014-02-17T09:26:54.0Z", 
    "source_id": "360296", 
    "source_catalog": "EMSC-RTS", 
    "flynn_region": "SWITZERLAND"
  }
},{
  "geometry": {
    "type": "Point", 
    "coordinates": [
      9.18, 
      47.43, 
      -2.0
    ]
  }, 
  "type": "Feature", 
  "id": "20140212_0000026", 
  "properties": {
    "lastupdate": "2014-02-12T11:05:00.0Z", 
    "magtype": "ml", 
    "evtype": "ke", 
    "lon": 9.18, 
    "auth": "ZUR", 
    "lat": 47.43, 
    "depth": 2.0, 
    "unid": "20140212_0000026", 
    "mag": 1.7, 
    "time": "2014-02-12T11:02:17.7Z", 
    "source_id": "359270", 
    "source_catalog": "EMSC-RTS", 
    "flynn_region": "SWITZERLAND"
  }
},{
  "geometry": {
    "type": "Point", 
    "coordinates": [
      9.5, 
      47.07, 
      -7.0
    ]
  }, 
  "type": "Feature", 
  "id": "20140212_0000009", 
  "properties": {
    "lastupdate": "2014-02-12T05:53:00.0Z", 
    "magtype": "ml", 
    "evtype": "ke", 
    "lon": 9.5, 
    "auth": "ZUR", 
    "lat": 47.07, 
    "depth": 7.0, 
    "unid": "20140212_0000009", 
    "mag": 1.7, 
    "time": "2014-02-12T05:49:42.0Z", 
    "source_id": "359221", 
    "source_catalog": "EMSC-RTS", 
    "flynn_region": "LIECHTENSTEIN"
  }
},{
  "geometry": {
    "type": "Point", 
    "coordinates": [
      9.51, 
      47.07, 
      -8.0
    ]
  }, 
  "type": "Feature", 
  "id": "20140212_0000008", 
  "properties": {
    "lastupdate": "2014-02-12T04:06:00.0Z", 
    "magtype": "ml", 
    "evtype": "ke", 
    "lon": 9.51, 
    "auth": "ZUR", 
    "lat": 47.07, 
    "depth": 8.0, 
    "unid": "20140212_0000008", 
    "mag": 1.7, 
    "time": "2014-02-12T04:02:46.1Z", 
    "source_id": "359218", 
    "source_catalog": "EMSC-RTS", 
    "flynn_region": "LIECHTENSTEIN"
  }
},{
  "geometry": {
    "type": "Point", 
    "coordinates": [
      8.92, 
      47.94, 
      -4.0
    ]
  }, 
  "type": "Feature", 
  "id": "20140210_0000088", 
  "properties": {
    "lastupdate": "2014-02-10T14:48:00.0Z", 
    "magtype": "ml", 
    "evtype": "ke", 
    "lon": 8.92, 
    "auth": "ZUR", 
    "lat": 47.94, 
    "depth": 4.0, 
    "unid": "20140210_0000088", 
    "mag": 1.9, 
    "time": "2014-02-10T14:45:14.7Z", 
    "source_id": "358954", 
    "source_catalog": "EMSC-RTS", 
    "flynn_region": "GERMANY"
  }
},{
  "geometry": {
    "type": "Point", 
    "coordinates": [
      6.9, 
      46.7, 
      1.0
    ]
  }, 
  "type": "Feature", 
  "id": "20140206_0000095", 
  "properties": {
    "lastupdate": "2014-02-07T09:09:00.0Z", 
    "magtype": "ml", 
    "evtype": "ke", 
    "lon": 6.9, 
    "auth": "ZUR", 
    "lat": 46.7, 
    "depth": -1.0, 
    "unid": "20140206_0000095", 
    "mag": 1.8, 
    "time": "2014-02-06T02:27:35.4Z", 
    "source_id": "358323", 
    "source_catalog": "EMSC-RTS", 
    "flynn_region": "SWITZERLAND"
  }
},{
  "geometry": {
    "type": "Point", 
    "coordinates": [
      7.31, 
      47.19, 
      -50.0
    ]
  }, 
  "type": "Feature", 
  "id": "20140205_0000064", 
  "properties": {
    "lastupdate": "2014-02-05T15:17:00.0Z", 
    "magtype": "ml", 
    "evtype": "ke", 
    "lon": 7.31, 
    "auth": "ZUR", 
    "lat": 47.19, 
    "depth": 50.0, 
    "unid": "20140205_0000064", 
    "mag": 2.2, 
    "time": "2014-02-05T15:12:11.4Z", 
    "source_id": "357934", 
    "source_catalog": "EMSC-RTS", 
    "flynn_region": "SWITZERLAND"
  }
},{
  "geometry": {
    "type": "Point", 
    "coordinates": [
      7.3, 
      47.19, 
      -40.0
    ]
  }, 
  "type": "Feature", 
  "id": "20140204_0000079", 
  "properties": {
    "lastupdate": "2014-02-04T15:06:00.0Z", 
    "magtype": "ml", 
    "evtype": "ke", 
    "lon": 7.3, 
    "auth": "ZUR", 
    "lat": 47.19, 
    "depth": 40.0, 
    "unid": "20140204_0000079", 
    "mag": 2.1, 
    "time": "2014-02-04T15:02:48.1Z", 
    "source_id": "357706", 
    "source_catalog": "EMSC-RTS", 
    "flynn_region": "SWITZERLAND"
  }
}]}